gohlkegrabber/__init__.py
gohlkegrabber/gohlkegrabber.py
gohlkegrabber-0.2.9.dist-info/LICENSE.txt
gohlkegrabber-0.2.9.dist-info/METADATA
gohlkegrabber-0.2.9.dist-info/WHEEL
gohlkegrabber-0.2.9.dist-info/entry_points.txt
gohlkegrabber-0.2.9.dist-info/top_level.txt
gohlkegrabber-0.2.9.dist-info/RECORD
