Metadata-Version: 2.1
Name: gohlkegrabber
Version: 0.2.9
Summary: Simple script to download .whl packages from www.lfd.uci.edu/~gohlke/pythonlibs.
Home-page: https://github.com/jaapvandervelde/gohlkegrabber
Author: BMT, Jaap van der Velde
Author-email: jaap.vandervelde@bmtglobal.com
License: MIT
Download-URL: https://github.com/jaapvandervelde/gohlkegrabber/archive/v0.2.9.tar.gz
Keywords: package,download,gohlke,wheel
Platform: UNKNOWN
Classifier: Development Status :: 4 - Beta
Classifier: Intended Audience :: Developers
Classifier: Topic :: Software Development :: Build Tools
Classifier: License :: OSI Approved :: MIT License
Classifier: Programming Language :: Python :: 3.7
Requires-Dist: lxml (>=4.4.2)
